README.rst
setup.py
bin/post-schemas
heimdallr_client/__init__.py
heimdallr_client/clients.py
heimdallr_client/exceptions.py
heimdallr_client/settings.py
heimdallr_client/utils.py
py_heimdallr_client.egg-info/PKG-INFO
py_heimdallr_client.egg-info/SOURCES.txt
py_heimdallr_client.egg-info/dependency_links.txt
py_heimdallr_client.egg-info/requires.txt
py_heimdallr_client.egg-info/top_level.txt
tests/__init__.py