Metadata-Version: 1.1
Name: py-heimdallr-client
Version: 0.0.2
Summary: Python API for Heimdallr
Home-page: https://github.com/ElementRobot/py-heimdallr-client
Author: Element Robot LLC
Author-email: dev@elementrobot.co
License: MIT
Keywords: heimdallr,rtc,websockets
Platform: UNKNOWN
Classifier: Development Status :: 3 - Alpha
Classifier: License :: OSI Approved :: MIT License
Classifier: Programming Language :: Python :: 2.6
Classifier: Intended Audience :: Developers
Classifier: Topic :: Software Development :: Build Tools
